delpha_db_manager/__all__.py
delpha_db_manager/__init__.py
delpha_db_manager/settings.py
delpha_db_manager/.ipynb_checkpoints/__all__-checkpoint.py
delpha_db_manager/.ipynb_checkpoints/__init__-checkpoint.py
delpha_db_manager/.ipynb_checkpoints/settings-checkpoint.py
delpha_db_manager/__pycache__/__init__.cpython-38.pyc
delpha_db_manager/__pycache__/settings.cpython-38.pyc
delpha_db_manager/core/__init__.py
delpha_db_manager/core/appflowmanager.py
delpha_db_manager/core/core.py
delpha_db_manager/core/operations.py
delpha_db_manager/core/s3manager.py
delpha_db_manager/core/.ipynb_checkpoints/__init__-checkpoint.py
delpha_db_manager/core/.ipynb_checkpoints/appflowmanager-checkpoint.py
delpha_db_manager/core/.ipynb_checkpoints/core-checkpoint.py
delpha_db_manager/core/.ipynb_checkpoints/operations-checkpoint.py
delpha_db_manager/core/.ipynb_checkpoints/s3manager-checkpoint.py
delpha_db_manager/core/__pycache__/__init__.cpython-38.pyc
delpha_db_manager/core/__pycache__/core.cpython-38.pyc
delpha_db_manager/core/__pycache__/operations.cpython-38.pyc
delpha_db_manager/credentials/cluster_delpha.pem
delpha_db_manager/utils/__init__.py
delpha_db_manager/utils/aws.py
delpha_db_manager/utils/.ipynb_checkpoints/__init__-checkpoint.py
delpha_db_manager/utils/.ipynb_checkpoints/aws-checkpoint.py
delpha_db_manager/utils/__pycache__/__init__.cpython-38.pyc
delpha_db_manager/utils/__pycache__/aws.cpython-38.pyc
delpha_db_manager-1.2.1.dist-info/LICENSE
delpha_db_manager-1.2.1.dist-info/METADATA
delpha_db_manager-1.2.1.dist-info/WHEEL
delpha_db_manager-1.2.1.dist-info/top_level.txt
delpha_db_manager-1.2.1.dist-info/zip-safe
delpha_db_manager-1.2.1.dist-info/RECORD
