Metadata-Version: 2.1
Name: delpha-db-manager
Version: 1.2.1
Summary: Delpha Database Management System
Home-page: https://github.com/Delpha-Assistant/DelphaDBManagement
Author: Hugo Paigneau
Author-email: hugo.paigneau@delpha.io
License: MIT
Keywords: database,salesforce api,cassandra api,aws api
Platform: UNKNOWN
Classifier: Intended Audience :: Developers
Classifier: License :: OSI Approved :: MIT License
Classifier: Operating System :: OS Independent
Classifier: Programming Language :: Python
Classifier: Programming Language :: Python :: 3
Classifier: Topic :: Software Development :: Libraries :: Python Modules
Requires-Dist: requests
Requires-Dist: xmltodict
Requires-Dist: url-normalize
Requires-Dist: cassandra-driver
Requires-Dist: pandas
Requires-Dist: simple-salesforce
Requires-Dist: boto3
